sumit_sdk/__init__.py
sumit_sdk/api.py
sumit_sdk/api_helper.py
sumit_sdk/base_task.py
sumit_sdk/exceptions.py
sumit_sdk/realtime_stt.py
sumit_sdk/storage.py
sumit_sdk/stream_stt.py
sumit_sdk/sumit_reckit.py
sumit_sdk/summary_api.py
sumit_sdk/transcript.py
sumit_sdk/translate_api.py
sumit_sdk/translate_subtitles.py
sumit_sdk/users.py
sumit_sdk/utils.py
sumit_sdk/utils/__init__.py
sumit_sdk/utils/alsa_recorder.py
sumit_sdk/utils/audio_helper.py
sumit_sdk/utils/downsample_helper.py
sumit_sdk/utils/socketio_client.py
sumit_sdk/utils/streamlink_helper.py
sumit_sdk-1.2.6.dist-info/licenses/LICENSE
sumit_sdk-1.2.6.dist-info/METADATA
sumit_sdk-1.2.6.dist-info/WHEEL
sumit_sdk-1.2.6.dist-info/top_level.txt
sumit_sdk-1.2.6.dist-info/RECORD
