Metadata-Version: 2.4
Name: sumit_sdk
Version: 1.2.6
Summary: SDK to communicate with sumit API
Author-email: Sumit-AI <shlomi@sumit-ai.com>
License-Expression: BSD-3-Clause
Project-URL: Homepage, https://www.sumit-x.com
Project-URL: Github, https://github.com/sumit-x-ai/sumit-sdk
Classifier: Development Status :: 3 - Alpha
Classifier: Intended Audience :: Developers
Classifier: Programming Language :: Python :: 3
Classifier: Programming Language :: Python :: 3.8
Classifier: Programming Language :: Python :: 3.9
Classifier: Programming Language :: Python :: 3.10
Classifier: Programming Language :: Python :: 3.11
Classifier: Programming Language :: Python :: 3.12
Classifier: Programming Language :: Python :: 3.13
Classifier: Programming Language :: Python :: 3.14
Requires-Python: >=3.8
License-File: LICENSE
Requires-Dist: requests>=2.25.0
Requires-Dist: websocket-client>=1.5.0
Requires-Dist: retry>=0.9.2
Requires-Dist: python-socketio>=5.10.0
Requires-Dist: numpy<2.0.0,>=1.24.0
Provides-Extra: audio
Requires-Dist: PyAudio; extra == "audio"
Requires-Dist: pyalsaaudio; extra == "audio"
Dynamic: license-file
